<?xml version="1.0" encoding="utf-8"?>
<annotation>
    <folder>output</folder>
    <filename>Balloon_Speed_Boat_12_4286_D931_E80_A65_X-47Y-14_HD270_case029_Tb_H_aug10_T0_G1_P1_R1.png</filename>
    <size>
        <width>640</width>
        <height>640</height>
        <depth>1</depth>
    </size>
    <segmented>0</segmented>
    <object>
        <name>ship</name>
        <pose>Unspecified</pose>
        <truncated>0</truncated>
        <difficult>0</difficult>
        <bndbox>
            <xmin>354</xmin>
            <ymin>262</ymin>
            <xmax>380</xmax>
            <ymax>292</ymax>
        </bndbox>
    </object>
    <object>
        <name>wake</name>
        <pose>Unspecified</pose>
        <truncated>0</truncated>
        <difficult>0</difficult>
        <bndbox>
            <xmin>358</xmin>
            <ymin>275</ymin>
            <xmax>542</xmax>
            <ymax>554</ymax>
        </bndbox>
    </object>
</annotation>
