<?xml version="1.0" encoding="utf-8"?>
<annotation>
    <folder>output</folder>
    <filename>Balloon_Speed_Boat_12_4286_D882_E72_A335_X-101Y-92_HD135_case087_Tb_H_aug10_T0_G1_P1_R1.png</filename>
    <size>
        <width>640</width>
        <height>640</height>
        <depth>1</depth>
    </size>
    <segmented>0</segmented>
    <object>
        <name>ship</name>
        <pose>Unspecified</pose>
        <truncated>0</truncated>
        <difficult>0</difficult>
        <bndbox>
            <xmin>140</xmin>
            <ymin>236</ymin>
            <xmax>165</xmax>
            <ymax>267</ymax>
        </bndbox>
    </object>
    <object>
        <name>wake</name>
        <pose>Unspecified</pose>
        <truncated>0</truncated>
        <difficult>0</difficult>
        <bndbox>
            <xmin>98</xmin>
            <ymin>251</ymin>
            <xmax>162</xmax>
            <ymax>485</ymax>
        </bndbox>
    </object>
</annotation>
