<?xml version="1.0" encoding="utf-8"?>
<annotation>
    <folder>output</folder>
    <filename>Carnival_Spirit_321_9792_D1526_E69_A11_X-83Y-33_HD305_case015_Tb_H_aug10_T0_G1_P1_R1.png</filename>
    <size>
        <width>640</width>
        <height>640</height>
        <depth>1</depth>
    </size>
    <segmented>0</segmented>
    <object>
        <name>ship</name>
        <pose>Unspecified</pose>
        <truncated>0</truncated>
        <difficult>0</difficult>
        <bndbox>
            <xmin>171</xmin>
            <ymin>192</ymin>
            <xmax>419</xmax>
            <ymax>313</ymax>
        </bndbox>
    </object>
    <object>
        <name>wake</name>
        <pose>Unspecified</pose>
        <truncated>0</truncated>
        <difficult>0</difficult>
        <bndbox>
            <xmin>396</xmin>
            <ymin>108</ymin>
            <xmax>542</xmax>
            <ymax>234</ymax>
        </bndbox>
    </object>
</annotation>
