<?xml version="1.0" encoding="utf-8"?>
<annotation>
    <folder>output</folder>
    <filename>coastal_freighterB_169_9786_D1712_E73_A290_X60Y47_HD50_case086_Tb_H_aug10_T0_G1_P1_R1.png</filename>
    <size>
        <width>640</width>
        <height>640</height>
        <depth>1</depth>
    </size>
    <segmented>0</segmented>
    <object>
        <name>ship</name>
        <pose>Unspecified</pose>
        <truncated>0</truncated>
        <difficult>0</difficult>
        <bndbox>
            <xmin>343</xmin>
            <ymin>254</ymin>
            <xmax>459</xmax>
            <ymax>330</ymax>
        </bndbox>
    </object>
    <object>
        <name>wake</name>
        <pose>Unspecified</pose>
        <truncated>0</truncated>
        <difficult>0</difficult>
        <bndbox>
            <xmin>98</xmin>
            <ymin>316</ymin>
            <xmax>335</xmax>
            <ymax>554</ymax>
        </bndbox>
    </object>
</annotation>
