<?xml version="1.0" encoding="utf-8"?>
<annotation>
    <folder>output</folder>
    <filename>Gemi_115_14226_D898_E50_A190_X166Y95_HD100_case074_Tb_H_aug10_T0_G1_P1_R1.png</filename>
    <size>
        <width>640</width>
        <height>640</height>
        <depth>1</depth>
    </size>
    <segmented>0</segmented>
    <object>
        <name>ship</name>
        <pose>Unspecified</pose>
        <truncated>0</truncated>
        <difficult>0</difficult>
        <bndbox>
            <xmin>180</xmin>
            <ymin>120</ymin>
            <xmax>332</xmax>
            <ymax>169</ymax>
        </bndbox>
    </object>
    <object>
        <name>wake</name>
        <pose>Unspecified</pose>
        <truncated>0</truncated>
        <difficult>0</difficult>
        <bndbox>
            <xmin>282</xmin>
            <ymin>130</ymin>
            <xmax>528</xmax>
            <ymax>184</ymax>
        </bndbox>
    </object>
</annotation>
