<?xml version="1.0" encoding="utf-8"?>
<annotation>
    <folder>output</folder>
    <filename>Gemi_115_14226_D1509_E76_A69_X-9Y-171_HD325_case069_Tb_H_aug10_T0_G1_P1_R0.png</filename>
    <size>
        <width>640</width>
        <height>640</height>
        <depth>1</depth>
    </size>
    <segmented>0</segmented>
    <object>
        <name>ship</name>
        <pose>Unspecified</pose>
        <truncated>0</truncated>
        <difficult>0</difficult>
        <bndbox>
            <xmin>238</xmin>
            <ymin>179</ymin>
            <xmax>341</xmax>
            <ymax>224</ymax>
        </bndbox>
    </object>
    <object>
        <name>wake</name>
        <pose>Unspecified</pose>
        <truncated>0</truncated>
        <difficult>0</difficult>
        <bndbox>
            <xmin>300</xmin>
            <ymin>191</ymin>
            <xmax>542</xmax>
            <ymax>322</ymax>
        </bndbox>
    </object>
</annotation>
